gitmap/__init__.py
gitmap/base.py
gitmap-0.0.1.dist-info/LICENSE
gitmap-0.0.1.dist-info/METADATA
gitmap-0.0.1.dist-info/WHEEL
gitmap-0.0.1.dist-info/top_level.txt
gitmap-0.0.1.dist-info/RECORD
