Metadata-Version: 2.1
Name: gitmap
Version: 0.0.1
Summary: GitMap: Map git commits to new commits, preserving history.
Home-page: https://github.com/yuantailing/gitmap
Author: Tailing Yuan
Author-email: yuantailing@gmail.com
License: UNKNOWN
Platform: UNKNOWN
Classifier: Programming Language :: Python :: 3
Classifier: License :: OSI Approved :: BSD License
Classifier: Operating System :: OS Independent
Requires-Python: >=3.4
Requires-Dist: git-python
Requires-Dist: gitdb
